pydantic_gql/__init__.py
pydantic_gql/base_vars.py
pydantic_gql/builders/__init__.py
pydantic_gql/builders/args_builder.py
pydantic_gql/builders/builder.py
pydantic_gql/builders/fields_builder.py
pydantic_gql/builders/indentation.py
pydantic_gql/builders/operation_builder.py
pydantic_gql/builders/type_builder.py
pydantic_gql/builders/value_builder.py
pydantic_gql/builders/vars_builder.py
pydantic_gql/connections.py
pydantic_gql/gql_field.py
pydantic_gql/mutation.py
pydantic_gql/operation.py
pydantic_gql/py.typed
pydantic_gql/query.py
pydantic_gql/values.py
pydantic_gql/var.py
pydantic_gql-1.2.2.dist-info/LICENSE
pydantic_gql-1.2.2.dist-info/METADATA
pydantic_gql-1.2.2.dist-info/WHEEL
pydantic_gql-1.2.2.dist-info/RECORD
