Metadata-Version: 2.1
Name: pydantic-gql
Version: 1.2.2
Summary: A simple GraphQL query builder based on Pydantic models
Home-page: https://github.com/abrahammurciano/pydantic-gql
License: GPLv3
Author: Abraham Murciano
Author-email: abrahammurciano@gmail.com
Requires-Python: >=3.12
Classifier: License :: Other/Proprietary License
Classifier: Programming Language :: Python :: 3
Classifier: Programming Language :: Python :: 3.12
Classifier: Programming Language :: Python :: 3.13
Requires-Dist: pydantic (>=2.9.2,<3.0.0)
Project-URL: Documentation, https://abrahammurciano.github.io/pydantic-gql/pydantic-gql
Project-URL: Repository, https://github.com/abrahammurciano/pydantic-gql
